{
    "tournament_info": [
        {
            "liquipediatier": "2",
            "name": "Saudi eLeague 2023 Season 1",
            "tickername": "Saudi eLeague 2023: Season 1",
            "shortname": "SEL 2023 S1",
            "image": "Saudi eLeague allmode.png",
            "icon": "Saudi eLeague icon allmode.png",
            "organizer": "SEF",
            "organizer-link": "https://saudiesports.sa/en/",
            "organizer2": "Savvy Games Group",
            "game": "overwatch2",
            "series": "Saudi eLeagues",
            "abbreviation": "SEL",
            "sponsor": "[https://mea.mastercard.com/en-region-mea.html Mastercard]",
            "sponsor2": "[https://www.stcplay.gg/ stc play]",
            "type": "Offline",
            "country": "Saudi Arabia",
            "city": "Riyadh",
            "venue": "[https://saudimediacity.tv/en/home-en/ SEF Arena]",
            "prizepool": "400,000",
            "localcurrency": "sar",
            "sdate": "2023-05-04",
            "edate": "2023-05-20",
            "web": "https://saudieleagues.sa/en/",
            "facebook": "SaudiELeagues",
            "youtube": "channel/UC6h42-fNpHCzm2hFR6_hbdg",
            "instagram": "saudieleague",
            "twitter": "SaudieLeagues",
            "twitch": "saudieleagues",
            "tiktok": "saudieleague",
            "team_number": "8",
            "previous": "Saudi eLeagues/2022/Season 2 {{!}} 2022 S2",
            "next": ""
        }
    ],
    "team_cards": [
        {
            "team": "Vision Esports",
            "p1": "Love",
            "pos1": "dps",
            "p2": "Mesopos",
            "pos2": "dps",
            "p3": "Francium",
            "pos3": "tank",
            "p4": "SPEEDY",
            "pos4": "sup",
            "p5": "Inviktonizer",
            "pos5": "sup",
            "t2title": "Staff",
            "t2c1": "Natdoekje",
            "t2c1pos": "coach",
            "t2c2": "Skeng1",
            "t2c2pos": "manager",
            "t3title": "Substitute",
            "t3p1": "KORZ",
            "t3pos1": "dps",
            "t3p2": "Zero",
            "t3p2flag": "sa",
            "t3pos2": "sup",
            "t3p2link": "Zero (Saudi Arabian player)",
            "qualifier": "[[Saudi_eLeague/2023/Season_1_Open_Qualifier|Qualifier Group A]]",
            "placementicon": "{{LeagueIconSmall/saudi eleague 2023}}",
            "placement": "3",
            "inotes": "{{NoteBig",
            "n1": "[[Vision Esports]] aquires [[HUSIS'S TEAM]] spot."
        },
        {
            "team": "FOG E-SPORTS",
            "p1": "slowdive",
            "pos1": "dps",
            "p2": "Miraculous",
            "pos2": "dps",
            "p3": "Meshoxv",
            "pos3": "tank",
            "p4": "Skatai",
            "pos4": "sup",
            "p5": "Musashi",
            "pos5": "sup",
            "t2title": "Staff",
            "t2c1": "Levitate",
            "t2c1pos": "coach",
            "t2c2": "Klinz",
            "t2c2flag": "sa",
            "t2c2pos": "manager",
            "qualifier": "[[Saudi_eLeague/2023/Season_1_Open_Qualifier|Qualifier Group A]]",
            "placementicon": "{{LeagueIconSmall/saudi eleague 2023}}",
            "placement": "4",
            "inotes": "{{NoteBig",
            "n1": "[[FOG E-SPORTS]] aquires [[Elden Lords]] spot."
        },
        {
            "team": "ROC Esports",
            "p1": "Fuki",
            "pos1": "dps",
            "p2": "Sazuri",
            "pos2": "dps",
            "p3": "Ailiseu",
            "pos3": "tank",
            "p4": "ANJ",
            "pos4": "sup",
            "p5": "Facator",
            "pos5": "sup",
            "t2title": "Staff",
            "t2c1": "Kayszan",
            "t2c1pos": "manager",
            "t2c2": "Ducklover",
            "t2c2pos": "manager",
            "t2c3": "Lotsha",
            "t2c3pos": "manager",
            "t3title": "Substitute",
            "t3p1": "BlackSwordz",
            "t3pos1": "Tank",
            "t3p2": "AOY",
            "t3pos2": "sup",
            "qualifier": "[[Saudi_eLeague/2023/Season_1_Open_Qualifier|Qualifier Group B]]",
            "placementicon": "{{LeagueIconSmall/saudi eleague 2023}}",
            "placement": "3"
        },
        {
            "team": "F16 Esports",
            "p1": "h1ra",
            "pos1": "dps",
            "p2": "Goku",
            "pos2": "dps",
            "p3": "Kayeose",
            "pos3": "tank",
            "p4": "TaR1GeT",
            "pos4": "sup",
            "p5": "Scyle",
            "pos5": "sup",
            "t2title": "Staff",
            "t2c1": "Beasthalo",
            "t2c1pos": "coach",
            "t2c2": "Skeng1",
            "t2c2pos": "manager",
            "t3title": "Substitute",
            "t3p1": "Ricin",
            "t3pos1": "tank",
            "qualifier": "[[Saudi_eLeague/2023/Season_1_Open_Qualifier|Qualifier Group B]]",
            "placementicon": "{{LeagueIconSmall/saudi eleague 2023}}",
            "placement": "4",
            "inotes": "{{NoteBig",
            "n1": "[[F16 Esports]] aquires [[SZR]] spot."
        }
    ],
    "match_cards": [
        {
            "bestof": "5",
            "date": "May 4, 2023 - 17:00",
            "date_timezone": "CEST",
            "youtube": "SaudieLeagues",
            "twitch": "Saudi eLeagues",
            "opponent1": "F16 Esports",
            "opponent2": "Triple Esports",
            "map1": {
                "map": "Ilios",
                "mode": "Control",
                "score1": "0",
                "score2": "2",
                "winner": "2",
                "vod": "https://www.twitch.tv/videos/1811106024?t=04h06m28s"
            },
            "map2": {
                "map": "King's Row",
                "mode": "Hybrid",
                "score1": "1",
                "score2": "3",
                "winner": "2",
                "vod": "https://www.twitch.tv/videos/1811106024?t=04h23m10s"
            },
            "map3": {
                "map": "Shambali Monastery",
                "mode": "Escort",
                "score1": "2",
                "score2": "3",
                "winner": "2",
                "vod": "https://www.twitch.tv/videos/1811106024?t=04h53m28s"
            },
            "optional": "M1="
        },
        {
            "date": "May 4, 2023 - 18:30",
            "date_timezone": "CEST",
            "youtube": "SaudieLeagues",
            "twitch": "Saudi eLeagues",
            "opponent1": "Triple Esports",
            "opponent2": "Chimera Esports",
            "map1": {
                "map": "Ilios",
                "mode": "Control",
                "score1": "2",
                "score2": "1",
                "winner": "1",
                "vod": "https://www.youtube.com/live/SIRN5APsoN4?feature=share&t=20994"
            },
            "map2": {
                "map": "Blizzard World",
                "mode": "Hybrid",
                "score1": "1",
                "score2": "0",
                "winner": "1",
                "vod": "https://www.youtube.com/live/SIRN5APsoN4?feature=share&t=22669"
            },
            "map3": {
                "map": "Rialto",
                "mode": "Escort",
                "score1": "3",
                "score2": "2",
                "winner": "1",
                "vod": "https://www.youtube.com/live/SIRN5APsoN4?feature=share&t=24013"
            },
            "optional": "M2="
        },
        {
            "date": "May 5, 2023 - 17:00",
            "date_timezone": "CEST",
            "youtube": "SaudieLeagues",
            "twitch": "Saudi eLeagues",
            "opponent1": "Vision Esports",
            "opponent2": "Chimera Esports",
            "map1": {
                "map": "Antarctic Peninsula",
                "mode": "Control",
                "score1": "0",
                "score2": "2",
                "winner": "2",
                "vod": "https://www.twitch.tv/videos/1811938580?t=02h35m19s"
            },
            "map2": {
                "map": "Blizzard World",
                "mode": "Hybrid",
                "score1": "1",
                "score2": "2",
                "winner": "2",
                "vod": "https://www.twitch.tv/videos/1811938580?t=02h53m01s"
            },
            "map3": {
                "map": "Rialto",
                "mode": "Escort",
                "score1": "1",
                "score2": "2",
                "winner": "2",
                "vod": "https://www.twitch.tv/videos/1811938580?t=03h21m15s"
            },
            "optional": "M3="
        },
        {
            "date": "May 5, 2023 - 18:30",
            "date_timezone": "CEST",
            "youtube": "SaudieLeagues",
            "twitch": "Saudi eLeagues",
            "opponent1": "Triple Esports",
            "opponent2": "Vision Esports",
            "map1": {
                "map": "Lijiang Tower",
                "mode": "Control",
                "score1": "2",
                "score2": "0",
                "winner": "1",
                "vod": "https://www.twitch.tv/videos/1811938580?t=04h12m35s"
            },
            "map2": {
                "map": "King's Row",
                "mode": "Hybrid",
                "score1": "4",
                "score2": "3",
                "winner": "1",
                "vod": "https://www.twitch.tv/videos/1811938580?t=04h25m00s"
            },
            "map3": {
                "map": "Rialto",
                "mode": "Escort",
                "score1": "3",
                "score2": "0",
                "winner": "1",
                "vod": "https://www.twitch.tv/videos/1811938580?t=05h00m06s"
            },
            "optional": "M4="
        },
        {
            "date": "May 6, 2023 - 15:20",
            "date_timezone": "CEST",
            "youtube": "SaudieLeagues",
            "twitch": "Saudi eLeagues",
            "opponent1": "Chimera Esports",
            "opponent2": "F16 Esports",
            "map1": {
                "map": "Ilios",
                "mode": "Control",
                "score1": "2",
                "score2": "1",
                "winner": "1",
                "vod": "https://www.twitch.tv/videos/1812827419?t=01h20m38s"
            },
            "map2": {
                "map": "King's Row",
                "mode": "Hybrid",
                "score1": "3",
                "score2": "1",
                "winner": "1",
                "vod": "https://www.twitch.tv/videos/1812827419?t=01h41m11s"
            },
            "map3": {
                "map": "Havana",
                "mode": "Escort",
                "score1": "2",
                "score2": "3",
                "winner": "2",
                "vod": "https://www.twitch.tv/videos/1812827419?t=02h03m34s"
            },
            "map4": {
                "map": "Colosseo",
                "mode": "Push",
                "score1": "68.04m",
                "score2": "72.44m",
                "winner": "2",
                "vod": "https://www.twitch.tv/videos/1812827419?t=02h31m19s"
            },
            "map5": {
                "map": "Oasis",
                "mode": "Control",
                "score1": "1",
                "score2": "2",
                "winner": "2",
                "vod": "https://www.twitch.tv/videos/1812827419?t=02h48m01s"
            },
            "optional": "M5="
        },
        {
            "date": "May 6, 2023 - 20:00",
            "date_timezone": "CEST",
            "youtube": "SaudieLeagues",
            "twitch": "Saudi eLeagues",
            "opponent1": "F16 Esports",
            "opponent2": "Vision Esports",
            "map1": {
                "map": "Oasis",
                "mode": "Control",
                "score1": "2",
                "score2": "0",
                "winner": "1",
                "vod": "https://www.twitch.tv/videos/1812827419?t=06h56m18s"
            },
            "map2": {
                "map": "Blizzard World",
                "mode": "Hybrid",
                "score1": "3",
                "score2": "0",
                "winner": "1",
                "vod": "https://www.twitch.tv/videos/1812827419?t=07h10m47s"
            },
            "map3": {
                "map": "Shambali Monastery",
                "mode": "Escort",
                "score1": "4",
                "score2": "3",
                "winner": "1",
                "vod": "https://www.twitch.tv/videos/1812827419?t=07h31m47s"
            },
            "optional": "M6="
        },
        {
            "bestof": "5",
            "date": "May 4, 2023 - 15:20",
            "date_timezone": "CEST",
            "youtube": "SaudieLeagues",
            "twitch": "Saudi eLeagues",
            "opponent1": "Onyx Ravens",
            "opponent2": "Twisted Minds",
            "map1": {
                "map": "Antarctic Peninsula",
                "mode": "Control",
                "score1": "0",
                "score2": "2",
                "winner": "2",
                "vod": "https://www.twitch.tv/videos/1811106024?t=02h09m48s"
            },
            "map2": {
                "map": "King's Row",
                "mode": "Hybrid",
                "score1": "3",
                "score2": "4",
                "winner": "2",
                "vod": "https://www.twitch.tv/videos/1811106024?t=02h25m45s"
            },
            "map3": {
                "map": "Rialto",
                "mode": "Escort",
                "score1": "0",
                "score2": "1",
                "winner": "2",
                "vod": "https://www.twitch.tv/videos/1811106024?t=03h09m50s"
            },
            "optional": "M1="
        },
        {
            "date": "May 4, 2023 - 20:00",
            "date_timezone": "CEST",
            "youtube": "SaudieLeagues",
            "twitch": "Saudi eLeagues",
            "opponent1": "Twisted Minds",
            "opponent2": "ROC Esports",
            "map1": {
                "map": "Oasis",
                "mode": "Control",
                "score1": "2",
                "score2": "0",
                "winner": "1",
                "vod": "https://www.twitch.tv/videos/1811326390?t=01h28m37s"
            },
            "map2": {
                "map": "King's Row",
                "mode": "Hybrid",
                "score1": "3",
                "score2": "2",
                "winner": "1",
                "vod": "https://www.twitch.tv/videos/1811326390?t=01h42m40s"
            },
            "map3": {
                "map": "Havana",
                "mode": "Escort",
                "score1": "1",
                "score2": "0",
                "winner": "1",
                "vod": "https://www.twitch.tv/videos/1811326390?t=02h07m19s"
            },
            "optional": "M2="
        },
        {
            "date": "May 5, 2023 - 15:20",
            "date_timezone": "CEST",
            "youtube": "SaudieLeagues",
            "twitch": "Saudi eLeagues",
            "opponent1": "Twisted Minds",
            "opponent2": "FOG Esports",
            "map1": {
                "map": "Ilios",
                "mode": "Control",
                "score1": "2",
                "score2": "0",
                "winner": "1",
                "vod": "https://www.twitch.tv/videos/1811938580?t=01h12m53s"
            },
            "map2": {
                "map": "Blizzard World",
                "mode": "Hybrid",
                "score1": "3",
                "score2": "0",
                "winner": "1",
                "vod": "https://www.twitch.tv/videos/1811938580?t=01h32m51s"
            },
            "map3": {
                "map": "Havana",
                "mode": "Escort",
                "score1": "1",
                "score2": "0",
                "winner": "1",
                "vod": "https://www.twitch.tv/videos/1811938580?t=01h51m50s"
            },
            "optional": "M3="
        },
        {
            "date": "May 5, 2023 - 20:00",
            "date_timezone": "CEST",
            "youtube": "SaudieLeagues",
            "twitch": "Saudi eLeagues",
            "opponent1": "FOG Esports",
            "opponent2": "Onyx Ravens",
            "map1": {
                "map": "Ilios",
                "mode": "Control",
                "score1": "0",
                "score2": "2",
                "winner": "2",
                "vod": "https://www.twitch.tv/videos/1811938580?t=05h51m40s"
            },
            "map2": {
                "map": "Hollywood",
                "mode": "Hybrid",
                "score1": "0",
                "score2": "3",
                "winner": "2",
                "vod": "https://www.twitch.tv/videos/1811938580?t=06h11m46s"
            },
            "map3": {
                "map": "Havana",
                "mode": "Escort",
                "score1": "0",
                "score2": "1",
                "winner": "2",
                "vod": "https://www.twitch.tv/videos/1811938580?t=06h33m11s"
            },
            "optional": "M4="
        },
        {
            "date": "May 6, 2023 - 17:00",
            "date_timezone": "CEST",
            "youtube": "SaudieLeagues",
            "twitch": "Saudi eLeagues",
            "opponent1": "ROC Esports",
            "opponent2": "FOG Esports",
            "map1": {
                "map": "Lijiang Tower",
                "mode": "Control",
                "score1": "2",
                "score2": "0",
                "winner": "1",
                "vod": "https://www.twitch.tv/videos/1812827419?t=03h48m32s"
            },
            "map2": {
                "map": "King's Row",
                "mode": "Hybrid",
                "score1": "3",
                "score2": "1",
                "winner": "1",
                "vod": "https://www.twitch.tv/videos/1812827419?t=04h03m22s"
            },
            "map3": {
                "map": "Havana",
                "mode": "Escort",
                "score1": "1",
                "score2": "0",
                "winner": "1",
                "vod": "https://www.twitch.tv/videos/1812827419?t=04h27m59s"
            },
            "optional": "M5="
        },
        {
            "date": "May 6, 2023 - 18:30",
            "date_timezone": "CEST",
            "youtube": "SaudieLeagues",
            "twitch": "Saudi eLeagues",
            "opponent1": "Onyx Ravens",
            "opponent2": "ROC Esports",
            "map1": {
                "map": "Oasis",
                "mode": "Control",
                "score1": "1",
                "score2": "2",
                "winner": "2",
                "vod": "https://www.twitch.tv/videos/1812827419?t=05h08m37s"
            },
            "map2": {
                "map": "King's Row",
                "mode": "Hybrid",
                "score1": "2",
                "score2": "3",
                "winner": "2",
                "vod": "https://www.twitch.tv/videos/1812827419?t=05h30m13s"
            },
            "map3": {
                "map": "Rialto",
                "mode": "Escort",
                "score1": "0",
                "score2": "1",
                "winner": "2",
                "vod": "https://www.twitch.tv/videos/1812827419?t=05h56m15s"
            },
            "optional": "M6="
        },
        {
            "bestof": "5",
            "date": "May 11, 2023 - 16:20",
            "date_timezone": "AST",
            "youtube": "SaudieLeagues",
            "twitch": "Saudi eLeagues",
            "opponent1": "ROC Esports",
            "opponent2": "Chimera Esports",
            "map1": {
                "map": "Lijiang Tower",
                "mode": "Control",
                "score1": "0",
                "score2": "2",
                "winner": "2",
                "vod": "https://www.twitch.tv/videos/1817062072?t=01h25m00s"
            },
            "map2": {
                "map": "King's Row",
                "mode": "Hybrid",
                "score1": "2",
                "score2": "3",
                "winner": "2",
                "vod": "https://www.twitch.tv/videos/1817062072?t=01h39m00s"
            },
            "map3": {
                "map": "Rialto",
                "mode": "Escort",
                "score1": "0",
                "score2": "1",
                "winner": "2",
                "vod": "https://www.twitch.tv/videos/1817062072?t=02h04m27s"
            },
            "optional": "R1M1="
        },
        {
            "date": "May 11, 2023 - 18:00",
            "date_timezone": "AST",
            "youtube": "SaudieLeagues",
            "twitch": "Saudi eLeagues",
            "opponent1": "F16 Esports",
            "opponent2": "Onyx Ravens",
            "map1": {
                "map": "Oasis",
                "mode": "Control",
                "score1": "2",
                "score2": "0",
                "winner": "1",
                "vod": "https://www.twitch.tv/videos/1817062072?t=03h07m04s"
            },
            "map2": {
                "map": "King's Row",
                "mode": "Hybrid",
                "score1": "3",
                "score2": "0",
                "winner": "1",
                "vod": "https://www.twitch.tv/videos/1817062072?t=3h21m15s"
            },
            "map3": {
                "map": "Shambali Monastery",
                "mode": "Escort",
                "score1": "3",
                "score2": "0",
                "winner": "1",
                "vod": "https://www.twitch.tv/videos/1817062072?t=3h40m0s"
            },
            "optional": "R1M2="
        },
        {
            "date": "May 12, 2023 - 16:20",
            "date_timezone": "AST",
            "youtube": "SaudieLeagues",
            "twitch": "Saudi eLeagues",
            "opponent1": "Triple Esports",
            "opponent2": "Chimera Esports",
            "map1": {
                "map": "Ilios",
                "mode": "Control",
                "score1": "2",
                "score2": "1",
                "winner": "1",
                "vod": "https://www.twitch.tv/videos/1817894506?t=1h27m37s"
            },
            "map2": {
                "map": "King's Row",
                "mode": "Hybrid",
                "score1": "3",
                "score2": "2",
                "winner": "1",
                "vod": "https://www.twitch.tv/videos/1817894506?t=1h48m2s"
            },
            "map3": {
                "map": "Rialto",
                "mode": "Escort",
                "score1": "3",
                "score2": "1",
                "winner": "1",
                "vod": "https://www.twitch.tv/videos/1817894506?t=2h20m14s"
            },
            "optional": "R2M1="
        },
        {
            "date": "May 12, 2023 - 18:00",
            "date_timezone": "AST",
            "youtube": "SaudieLeagues",
            "twitch": "Saudi eLeagues",
            "opponent1": "Twisted Minds",
            "opponent2": "F16 Esports",
            "map1": {
                "map": "Lijiang Tower",
                "mode": "Control",
                "score1": "0",
                "score2": "2",
                "winner": "2",
                "vod": "https://www.twitch.tv/videos/1817894506?t=3h26m27s"
            },
            "map2": {
                "map": "King's Row",
                "mode": "Hybrid",
                "score1": "4",
                "score2": "3",
                "winner": "1",
                "vod": "https://www.twitch.tv/videos/1817894506?t=3h44m41s"
            },
            "map3": {
                "map": "Havana",
                "mode": "Escort",
                "score1": "1",
                "score2": "0",
                "winner": "1",
                "vod": "https://www.twitch.tv/videos/1817894506?t=4h13m5s"
            },
            "map4": {
                "map": "Colosseo",
                "mode": "Push",
                "score1": "66.42m",
                "score2": "81.85m",
                "winner": "2",
                "vod": "https://www.twitch.tv/videos/1817894506?t=4h42m45s"
            },
            "map5": {
                "map": "Oasis",
                "mode": "Control",
                "score1": "2",
                "score2": "0",
                "winner": "1",
                "vod": "https://www.twitch.tv/videos/1817894506?t=5h0m9s"
            },
            "optional": "R2M2="
        },
        {
            "bestof": "7",
            "date": "May 19, 2023 - 18:00",
            "date_timezone": "AST",
            "youtube": "SaudieLeagues",
            "twitch": "Saudi eLeagues",
            "opponent1": "Triple Esports",
            "opponent2": "Twisted Minds",
            "map1": {
                "map": "Ilios",
                "mode": "Control",
                "score1": "0",
                "score2": "2",
                "winner": "2",
                "vod": "https://www.twitch.tv/videos/1823801233?t=3h18m35s"
            },
            "map2": {
                "map": "King's Row",
                "mode": "Hybrid",
                "score1": "2",
                "score2": "3",
                "winner": "2",
                "vod": "https://www.twitch.tv/videos/1823801233?t=3h35m23s"
            },
            "map3": {
                "map": "Rialto",
                "mode": "Escort",
                "score1": "1",
                "score2": "3",
                "winner": "2",
                "vod": "https://www.twitch.tv/videos/1823801233?t=3h58m48s"
            },
            "map4": {
                "map": "Colosseo",
                "mode": "Push",
                "score1": "86.19m",
                "score2": "90.24m",
                "winner": "2",
                "vod": "https://www.twitch.tv/videos/1823801233?t=4h28m14s"
            },
            "comment": "Rescheduled from May 18 due to severe weather near the venue",
            "optional": "R4M1="
        },
        {
            "bestof": "5",
            "date": "May 13, 2023 - 16:20",
            "date_timezone": "AST",
            "youtube": "SaudieLeagues",
            "twitch": "Saudi eLeagues",
            "opponent1": "F16 Esports",
            "opponent2": "ROC Esports",
            "map1": {
                "map": "Oasis",
                "mode": "Control",
                "score1": "2",
                "score2": "1",
                "winner": "1",
                "vod": "https://www.twitch.tv/videos/1818807204?t=1h22m38s"
            },
            "map2": {
                "map": "King's Row",
                "mode": "Hybrid",
                "score1": "3",
                "score2": "0",
                "winner": "1",
                "vod": "https://www.twitch.tv/videos/1818807204?t=1h43m40s"
            },
            "map3": {
                "map": "Shambali Monastery",
                "mode": "Escort",
                "score1": "3",
                "score2": "2",
                "winner": "1",
                "vod": "https://www.twitch.tv/videos/1818807204?t=2h1m38s"
            },
            "optional": "R2M3="
        },
        {
            "date": "May 13, 2023 - 18:00",
            "date_timezone": "AST",
            "youtube": "SaudieLeagues",
            "twitch": "Saudi eLeagues",
            "opponent1": "Chimera Esports",
            "opponent2": "Onyx Ravens",
            "map1": {
                "map": "Ilios",
                "mode": "Control",
                "score1": "2",
                "score2": "0",
                "winner": "1",
                "vod": "https://www.twitch.tv/videos/1818807204?t=2h59m12s"
            },
            "map2": {
                "map": "Hollywood",
                "mode": "Hybrid",
                "score1": "2",
                "score2": "1",
                "winner": "1",
                "vod": "https://www.twitch.tv/videos/1818807204?t=3h13m45s"
            },
            "map3": {
                "map": "Rialto",
                "mode": "Escort",
                "score1": "2",
                "score2": "1",
                "winner": "1",
                "vod": "https://www.twitch.tv/videos/1818807204?t=3h57m11s"
            },
            "optional": "R2M4="
        },
        {
            "date": "May 19, 2023 - 16:20",
            "date_timezone": "AST",
            "youtube": "SaudieLeagues",
            "twitch": "Saudi eLeagues",
            "opponent1": "F16 Esports",
            "opponent2": "Chimera Esports",
            "map1": {
                "map": "Oasis",
                "mode": "Control",
                "score1": "2",
                "score2": "1",
                "winner": "1",
                "vod": "https://www.twitch.tv/videos/1823801233?t=1h22m38s"
            },
            "map2": {
                "map": "Blizzard World",
                "mode": "Hybrid",
                "score1": "6",
                "score2": "5",
                "winner": "1",
                "vod": "https://www.twitch.tv/videos/1823801233?t=1h46m46s"
            },
            "map3": {
                "map": "Shambali Monastery",
                "mode": "Escort",
                "score1": "2",
                "score2": "0",
                "winner": "1",
                "vod": "https://www.twitch.tv/videos/1823801233?t=2h26m52s"
            },
            "comment": "Rescheduled from May 18 due to severe weather near the venue",
            "optional": "R3M1="
        },
        {
            "bestof": "7",
            "date": "May 19, 2023 - 20:00",
            "date_timezone": "AST",
            "youtube": "SaudieLeagues",
            "twitch": "Saudi eLeagues",
            "opponent1": "Triple Esports",
            "opponent2": "F16 Esports",
            "map1": {
                "map": "Ilios",
                "mode": "Control",
                "score1": "2",
                "score2": "0",
                "winner": "1",
                "vod": "https://www.twitch.tv/videos/1823801233?t=5h15m5s"
            },
            "map2": {
                "map": "King's Row",
                "mode": "Hybrid",
                "score1": "3",
                "score2": "1",
                "winner": "1",
                "vod": "https://www.twitch.tv/videos/1823801233?t=5h30m31s"
            },
            "map3": {
                "map": "Rialto",
                "mode": "Escort",
                "score1": "1",
                "score2": "0",
                "winner": "1",
                "vod": "https://www.twitch.tv/videos/1823801233?t=5h51m5s"
            },
            "map4": {
                "map": "Colosseo",
                "mode": "Push",
                "score1": "81.26m",
                "score2": "109.27m",
                "winner": "2",
                "vod": "https://www.twitch.tv/videos/1823801233?t=6h13m36s"
            },
            "map5": {
                "map": "Lijiang Tower",
                "mode": "Control",
                "score1": "2",
                "score2": "1",
                "winner": "1",
                "vod": "https://www.twitch.tv/videos/1823801233?t=6h33m39s"
            },
            "optional": "R4M2="
        },
        {
            "date": "May 20, 2023 - 18:40",
            "date_timezone": "AST",
            "youtube": "SaudieLeagues",
            "twitch": "Saudi eLeagues",
            "opponent1": "Twisted Minds",
            "opponent2": "Triple Esports",
            "map1": {
                "map": "Ilios",
                "mode": "Control",
                "score1": "2",
                "score2": "0",
                "winner": "1",
                "vod": "https://www.twitch.tv/videos/1824813788?t=0h8m30s"
            },
            "map2": {
                "map": "Blizzard World",
                "mode": "Hybrid",
                "score1": "0",
                "score2": "0",
                "winner": "",
                "vod": "https://www.twitch.tv/videos/1824813788?t=0h36m59s"
            },
            "map3": {
                "map": "Havana",
                "mode": "Escort",
                "score1": "1",
                "score2": "0",
                "winner": "1",
                "vod": "https://www.twitch.tv/videos/1824813788?t=0h57m12s"
            },
            "map4": {
                "map": "Colosseo",
                "mode": "Push",
                "score1": "106.00m",
                "score2": "81.31m",
                "winner": "1",
                "vod": "https://www.twitch.tv/videos/1824813788?t=1h23m58s"
            },
            "map5": {
                "map": "Nepal",
                "mode": "Control",
                "score1": "2",
                "score2": "0",
                "winner": "1",
                "vod": "https://www.twitch.tv/videos/1824813788?t=1h39m36s"
            },
            "optional": "R5M1="
        }
    ]
}