{
    "tournament_info": [
        {
            "liquipediatier": "5",
            "liquipediatiertype": "Qualifier",
            "series": "OWadria",
            "name": "RUR OWadria League Season 1 Qualifier #1",
            "shortname": "ROWAL S1 Qualifier #1",
            "image": "RowalLogo_Std.png",
            "icon": "Favicon owadria.png",
            "organizer": "OWadria",
            "organizer2": "Klanrur.rs",
            "sponsor": "Computerland",
            "country": "Croatia",
            "type": "Online",
            "bracket": "https://www.toornament.com/tournaments/58965a58140ba09d7a8b4573/stages/1/",
            "format": "",
            "prizepool": "",
            "prizepoolusd": "",
            "sdate": "2017-02-19",
            "edate": "2017-02-19",
            "twitch": "owadria",
            "twitter": "owadriaorg",
            "facebook": "blizzard.overwatch.adria",
            "youtube": "klanrur",
            "teamfirst": "",
            "teamsecond": "",
            "teamthird": "",
            "teamthird2": "",
            "team_number": "8"
        }
    ],
    "team_cards": [
        {
            "team": "Acertas Gaming",
            "p1": "sprEEEzy",
            "p1flag": "hr",
            "p2": "SkrakZ",
            "p2flag": "hr",
            "p3": "Doomzx",
            "p3flag": "rs",
            "p4": "Necros",
            "p4flag": "rs",
            "p5": "aRxEs",
            "p5flag": "hr",
            "p6": "Shamyx",
            "p6flag": "rs"
        },
        {
            "team": "TrokuT Gaming",
            "p1": "manky",
            "p1flag": "hr",
            "p2": "FRESHY",
            "p2flag": "hr",
            "p3": "noyyz",
            "p3flag": "hr",
            "p4": "neLo",
            "p4flag": "hr",
            "p5": "Ivekcina",
            "p5flag": "hr",
            "p6": "Lakii",
            "p6flag": "hr"
        },
        {
            "team": "TWB-Gaming",
            "p1": "Scentic",
            "p1flag": "hr",
            "p2": "Easymode",
            "p2flag": "rs",
            "p3": "kinko",
            "p3flag": "hr",
            "p4": "Leya",
            "p4flag": "si",
            "p5": "sfcMedo",
            "p5flag": "hr",
            "p6": "ZeRoQL",
            "p6flag": "rs"
        },
        {
            "team": "Povratak Otpisanih",
            "p1": "mixXxa",
            "p1flag": "hr",
            "p2": "PegazX",
            "p2flag": "hr",
            "p3": "Copeftw",
            "p3flag": "rs",
            "p4": "D33pinu",
            "p4flag": "hr",
            "p5": "MofoLoco",
            "p5flag": "hr",
            "p6": "Madrick",
            "p6flag": "rs"
        },
        {
            "team": "Useless Box",
            "p1": "Mudovaca",
            "p1flag": "hr",
            "p2": "alice",
            "p2flag": "hr",
            "p3": "swaglord420",
            "p3flag": "hr",
            "p4": "cayo",
            "p4flag": "hr",
            "p5": "vojnicina",
            "p5flag": "hr",
            "p6": "NoMercy",
            "p6flag": "hr"
        },
        {
            "team": "Krug",
            "p1": "MR4V",
            "p1flag": "rs",
            "p2": "Shock",
            "p2flag": "hr",
            "p3": "Sakurama",
            "p3flag": "hr",
            "p4": "Piglet",
            "p4flag": "rs",
            "p5": "Stalinski",
            "p5flag": "rs",
            "p6": "bexx",
            "p6flag": "hr"
        },
        {
            "team": "Banana Express",
            "p1": "localpolice",
            "p1flag": "hr",
            "p2": "BakaMraz",
            "p2flag": "hr",
            "p3": "Babajog",
            "p3flag": "hr",
            "p4": "Redd",
            "p4flag": "hr",
            "p5": "LordVxper",
            "p5flag": "hr",
            "p6": "Robertox",
            "p6flag": "hr"
        },
        {
            "team": "Team69",
            "p1": "Regieez",
            "p1flag": "hr",
            "p2": "squady",
            "p2flag": "rs",
            "p3": "KawaiiPanda",
            "p3flag": "rs",
            "p4": "RobiCRO",
            "p4flag": "hr",
            "p5": "Iris",
            "p5flag": "hr",
            "p6": "Avulsed",
            "p6flag": "ba"
        }
    ],
    "match_cards": []
}