{
    "tournament_info": [
        {
            "name": "The Overguard: Haste Overwatch $1k Series 5: Qualifier 1",
            "tickername": "Haste Overwatch $1k Series 5: Q1",
            "series": "The Overguard",
            "image": "Overguard Logo.png",
            "icon": "Overguard Logo small.png",
            "organizer": "The Overguard",
            "format": "Qualifiers <br> Single Elimination",
            "type": "Online",
            "country": "United States",
            "date": "2017-11-25",
            "prizepoolusd": "",
            "web": "https://battlefy.com/the-overguard/haste-overwatch-pc-1k-tournament-series-5/5a0a4faf63c91803484ded95/info?infoTab=details",
            "sponsor": "[https://haste.net/ Haste]",
            "twitch": "theoverguard",
            "twitter": "theoverguard",
            "bracket": "https://battlefy.com/the-overguard/haste-overwatch-pc-1k-tournament-series-5/5a0a4faf63c91803484ded95/stage/5a0a517c92796f09a27839e4/bracket/",
            "liquipediatier": "3",
            "liquipediatiertype": "Qualifier",
            "team_number": "25"
        }
    ],
    "team_cards": [
        {
            "team": "Toronto Esports",
            "image": "",
            "p1": "",
            "p1flag": " ",
            "pos1": "",
            "p2": "",
            "p2flag": " ",
            "pos2": "",
            "p3": "",
            "p3flag": " ",
            "pos3": "",
            "p4": "",
            "p4flag": " ",
            "pos4": "",
            "p5": "",
            "p5flag": " ",
            "pos5": "",
            "p6": "",
            "p6flag": " ",
            "pos6": "",
            "c": "",
            "cflag": ""
        },
        {
            "team": "NO ANIME ALLOWED",
            "image": "",
            "p1": "",
            "p1flag": " ",
            "pos1": "",
            "p2": "",
            "p2flag": " ",
            "pos2": "",
            "p3": "",
            "p3flag": " ",
            "pos3": "",
            "p4": "",
            "p4flag": " ",
            "pos4": "",
            "p5": "",
            "p5flag": " ",
            "pos5": "",
            "p6": "",
            "p6flag": " ",
            "pos6": "",
            "c": "",
            "cflag": ""
        },
        {
            "team": "The Savages",
            "image": "The Savages Red logo.png",
            "p1": "",
            "p1flag": " ",
            "pos1": "",
            "p2": "",
            "p2flag": " ",
            "pos2": "",
            "p3": "",
            "p3flag": " ",
            "pos3": "",
            "p4": "",
            "p4flag": " ",
            "pos4": "",
            "p5": "",
            "p5flag": " ",
            "pos5": "",
            "p6": "",
            "p6flag": " ",
            "pos6": "",
            "c": "",
            "cflag": ""
        },
        {
            "team": "Arizona State University",
            "p1": "Chumcha",
            "p1flag": "us",
            "pos1": "dps",
            "p2": "Amadien",
            "p2flag": "",
            "pos2": "dps",
            "p3": "ChroNoDotA",
            "p3flag": "",
            "pos3": "tank",
            "p4": "Spades",
            "p4flag": "us",
            "pos4": "tank",
            "p5": "chris",
            "p5flag": "us",
            "pos5": "sup",
            "p6": "djdobro",
            "p6flag": "us",
            "pos6": "sup"
        },
        {
            "team": "The Gatekeepers",
            "image": "",
            "p1": "",
            "p1flag": " ",
            "pos1": "",
            "p2": "",
            "p2flag": " ",
            "pos2": "",
            "p3": "",
            "p3flag": " ",
            "pos3": "",
            "p4": "",
            "p4flag": " ",
            "pos4": "",
            "p5": "",
            "p5flag": " ",
            "pos5": "",
            "p6": "",
            "p6flag": " ",
            "pos6": "",
            "c": "",
            "cflag": ""
        },
        {
            "team": "monkaGOD",
            "image": "",
            "p1": "",
            "p1flag": " ",
            "pos1": "",
            "p2": "",
            "p2flag": " ",
            "pos2": "",
            "p3": "",
            "p3flag": " ",
            "pos3": "",
            "p4": "",
            "p4flag": " ",
            "pos4": "",
            "p5": "",
            "p5flag": " ",
            "pos5": "",
            "p6": "",
            "p6flag": " ",
            "pos6": "",
            "c": "",
            "cflag": ""
        },
        {
            "team": "Full Send",
            "image": "",
            "p1": "",
            "p1flag": " ",
            "pos1": "",
            "p2": "",
            "p2flag": " ",
            "pos2": "",
            "p3": "",
            "p3flag": " ",
            "pos3": "",
            "p4": "",
            "p4flag": " ",
            "pos4": "",
            "p5": "",
            "p5flag": " ",
            "pos5": "",
            "p6": "",
            "p6flag": " ",
            "pos6": "",
            "c": "",
            "cflag": ""
        },
        {
            "team": "sinatraas christmas playlist",
            "image": "",
            "p1": "",
            "p1flag": " ",
            "pos1": "",
            "p2": "",
            "p2flag": " ",
            "pos2": "",
            "p3": "",
            "p3flag": " ",
            "pos3": "",
            "p4": "",
            "p4flag": " ",
            "pos4": "",
            "p5": "",
            "p5flag": " ",
            "pos5": "",
            "p6": "",
            "p6flag": " ",
            "pos6": "",
            "c": "",
            "cflag": ""
        },
        {
            "team": "Voltic Esports",
            "image": "Voltic Esports logo.png",
            "p1": "",
            "p1flag": " ",
            "pos1": "",
            "p2": "",
            "p2flag": " ",
            "pos2": "",
            "p3": "",
            "p3flag": " ",
            "pos3": "",
            "p4": "",
            "p4flag": " ",
            "pos4": "",
            "p5": "",
            "p5flag": " ",
            "pos5": "",
            "p6": "",
            "p6flag": " ",
            "pos6": "",
            "c": "",
            "cflag": ""
        },
        {
            "team": "ANT E-Sport",
            "image": "ANT E-Sports.png",
            "p1": "",
            "p1flag": " ",
            "pos1": "",
            "p2": "",
            "p2flag": " ",
            "pos2": "",
            "p3": "",
            "p3flag": " ",
            "pos3": "",
            "p4": "",
            "p4flag": " ",
            "pos4": "",
            "p5": "",
            "p5flag": " ",
            "pos5": "",
            "p6": "",
            "p6flag": " ",
            "pos6": "",
            "c": "",
            "cflag": ""
        },
        {
            "team": "Wild Rose Saint",
            "image": "",
            "p1": "",
            "p1flag": " ",
            "pos1": "",
            "p2": "",
            "p2flag": " ",
            "pos2": "",
            "p3": "",
            "p3flag": " ",
            "pos3": "",
            "p4": "",
            "p4flag": " ",
            "pos4": "",
            "p5": "",
            "p5flag": " ",
            "pos5": "",
            "p6": "",
            "p6flag": " ",
            "pos6": "",
            "c": "",
            "cflag": ""
        },
        {
            "team": "Hydra.OG",
            "image": "",
            "p1": "",
            "p1flag": " ",
            "pos1": "",
            "p2": "",
            "p2flag": " ",
            "pos2": "",
            "p3": "",
            "p3flag": " ",
            "pos3": "",
            "p4": "",
            "p4flag": " ",
            "pos4": "",
            "p5": "",
            "p5flag": " ",
            "pos5": "",
            "p6": "",
            "p6flag": " ",
            "pos6": "",
            "c": "",
            "cflag": ""
        },
        {
            "team": "CORE Hyperion",
            "image": "",
            "p1": "",
            "p1flag": " ",
            "pos1": "",
            "p2": "",
            "p2flag": " ",
            "pos2": "",
            "p3": "",
            "p3flag": " ",
            "pos3": "",
            "p4": "",
            "p4flag": " ",
            "pos4": "",
            "p5": "",
            "p5flag": " ",
            "pos5": "",
            "p6": "",
            "p6flag": " ",
            "pos6": "",
            "c": "",
            "cflag": ""
        },
        {
            "team": "Incede Red",
            "image": "",
            "p1": "",
            "p1flag": " ",
            "pos1": "",
            "p2": "",
            "p2flag": " ",
            "pos2": "",
            "p3": "",
            "p3flag": " ",
            "pos3": "",
            "p4": "",
            "p4flag": " ",
            "pos4": "",
            "p5": "",
            "p5flag": " ",
            "pos5": "",
            "p6": "",
            "p6flag": " ",
            "pos6": "",
            "c": "",
            "cflag": ""
        },
        {
            "team": "Latitude",
            "image": "",
            "p1": "",
            "p1flag": " ",
            "pos1": "",
            "p2": "",
            "p2flag": " ",
            "pos2": "",
            "p3": "",
            "p3flag": " ",
            "pos3": "",
            "p4": "",
            "p4flag": " ",
            "pos4": "",
            "p5": "",
            "p5flag": " ",
            "pos5": "",
            "p6": "",
            "p6flag": " ",
            "pos6": "",
            "c": "",
            "cflag": ""
        },
        {
            "team": "DPA",
            "image": "",
            "p1": "",
            "p1flag": " ",
            "pos1": "",
            "p2": "",
            "p2flag": " ",
            "pos2": "",
            "p3": "",
            "p3flag": " ",
            "pos3": "",
            "p4": "",
            "p4flag": " ",
            "pos4": "",
            "p5": "",
            "p5flag": " ",
            "pos5": "",
            "p6": "",
            "p6flag": " ",
            "pos6": "",
            "c": "",
            "cflag": ""
        }
    ],
    "legacy_match_cards": [
        {
            "team2": "no anime allowed",
            "score2": "2",
            "win2": "1",
            "key": "R1D1",
            "team1": "dpa",
            "score1": "0",
            "win1": ""
        },
        {
            "team2": "latitude",
            "score2": "0",
            "win2": "",
            "key": "R1D3",
            "team1": "the gatekeepers",
            "score1": "2",
            "win1": "1"
        },
        {
            "team2": "arizona state",
            "score2": "2",
            "win2": "1",
            "key": "R1D5",
            "team1": "incede red",
            "score1": "0",
            "win1": ""
        },
        {
            "team2": "core hyperion",
            "score2": "0",
            "win2": "",
            "key": "R1D7",
            "team1": "monkagod",
            "score1": "2",
            "win1": "1"
        },
        {
            "team2": "the savages",
            "score2": "2",
            "win2": "1",
            "key": "R1D9",
            "team1": "hydra.og",
            "score1": "0",
            "win1": ""
        },
        {
            "team2": "full send",
            "score2": "2",
            "win2": "1",
            "key": "R1D11",
            "team1": "wild rose saint",
            "score1": "0",
            "win1": ""
        },
        {
            "team2": "sinatraas christmas playlist",
            "score2": "2",
            "win2": "1",
            "key": "R1D13",
            "team1": "ant e-sport",
            "score1": "0",
            "win1": ""
        },
        {
            "team2": "voltic esports",
            "score2": "0",
            "win2": "",
            "key": "R1D15",
            "team1": "toronto esports",
            "score1": "2",
            "win1": "1"
        },
        {
            "team2": "the gatekeepers",
            "score2": "1",
            "win2": "",
            "key": "R2W1",
            "team1": "no anime allowed",
            "score1": "2",
            "win1": "1"
        },
        {
            "team2": "monkagod",
            "score2": "1",
            "win2": "",
            "key": "R2W3",
            "team1": "arizona state",
            "score1": "2",
            "win1": "1"
        },
        {
            "team2": "full send",
            "score2": "0",
            "win2": "",
            "key": "R2W5",
            "team1": "the savages",
            "score1": "2",
            "win1": "1"
        },
        {
            "team2": "toronto esports",
            "score2": "2",
            "win2": "1",
            "key": "R2W7",
            "team1": "sinatraas christmas playlist",
            "score1": "1",
            "win1": ""
        },
        {
            "team2": "arizona state",
            "score2": "0",
            "win2": "",
            "key": "R3W1",
            "team1": "no anime allowed",
            "score1": "2",
            "win1": "1"
        },
        {
            "team2": "toronto esports",
            "score2": "2",
            "win2": "1",
            "key": "R3W3",
            "team1": "the savages",
            "score1": "0",
            "win1": ""
        },
        {
            "team2": "toronto esports",
            "score2": "3",
            "win2": "1",
            "key": "R4W1",
            "team1": "no anime allowed",
            "score1": "0",
            "win1": ""
        },
        {
            "team2": "the savages",
            "score2": "2",
            "win2": "1",
            "key": "R4D1",
            "team1": "arizona state",
            "score1": "0",
            "win1": ""
        }
    ],
    "match_maps": []
}